sane_tikz/__init__.py
sane_tikz/core.py
sane_tikz/formatting.py
sane_tikz-0.1.dist-info/LICENSE.md
sane_tikz-0.1.dist-info/METADATA
sane_tikz-0.1.dist-info/WHEEL
sane_tikz-0.1.dist-info/top_level.txt
sane_tikz-0.1.dist-info/RECORD
