Metadata-Version: 2.1
Name: sane-tikz
Version: 0.1
Summary: Python to TikZ transpiler
Home-page: http://github.com/negrinho/sane_tikz
Author: Renato Negrinho
Author-email: renato.negrinho@gmail.com
License: MIT
Platform: UNKNOWN
Classifier: Intended Audience :: Science/Research
Classifier: Development Status :: 3 - Alpha
Classifier: License :: OSI Approved :: MIT License
Classifier: Programming Language :: Python :: 3.6
Classifier: Topic :: Scientific/Engineering :: Visualization
Requires-Python: >=3.6
Requires-Dist: numpy
